socks/__init__.py
socks/httpcore_wrapper.py
socks/socks.py
socks/utils.py
socks_uds-1.3.dist-info/LICENSE
socks_uds-1.3.dist-info/METADATA
socks_uds-1.3.dist-info/WHEEL
socks_uds-1.3.dist-info/top_level.txt
socks_uds-1.3.dist-info/RECORD
