Metadata-Version: 2.1
Name: socks-uds
Version: 1.3
Summary: Socks over Unix Domain Socket
Home-page: https://gitlab.com/balki/socks_uds
Author: balki
Author-email: socks_uds@balki.me
License: MPL
Keywords: socks,tor
Platform: any
Classifier: Framework :: AsyncIO
Classifier: License :: OSI Approved :: Mozilla Public License 2.0 (MPL 2.0)
Classifier: Topic :: Internet
Classifier: Topic :: Internet :: Proxy Servers
Classifier: Programming Language :: Python :: 3
Classifier: Programming Language :: Python :: 3.6
Classifier: Programming Language :: Python :: 3.7
Classifier: Programming Language :: Python :: 3.8
Classifier: Programming Language :: Python :: 3.9
